[{"patternid": 439, "pattern": {"id": 0, "feature": 3, "split": 2}},
{"patternid": 221, "pattern": {"id": 0, "feature": 51, "split": 6}},
{"patternid": 632, "pattern": {"id": 0, "feature": 39, "split": 1}},
{"patternid": 83, "pattern": {"id": 0, "feature": 55, "split": 24}},
{"patternid": 555, "pattern": {"id": 0, "feature": 51, "split": 8}},
{"patternid": 424, "pattern": {"id": 0, "feature": 55, "split": 44}},
{"patternid": 592, "pattern": {"id": 0, "feature": 46, "split": 1}},
{"patternid": 283, "pattern": {"id": 0, "feature": 56, "split": 2280}},
{"patternid": 564, "pattern": {"id": 0, "feature": 1, "split": 7}},
{"patternid": 454, "pattern": {"id": 0, "feature": 56, "split": 129}},
{"patternid": 450, "pattern": {"id": 0, "feature": 55, "split": 48}},
{"patternid": 493, "pattern": {"id": 0, "feature": 17, "split": 3}},
{"patternid": 367, "pattern": {"id": 0, "feature": 18, "split": 5}},
{"patternid": 590, "pattern": {"id": 0, "feature": 16, "split": 0}},
{"patternid": 460, "pattern": {"id": 0, "feature": 56, "split": 232}},
{"patternid": 218, "pattern": {"id": 0, "feature": 54, "split": 12}},
{"patternid": 430, "pattern": {"id": 0, "feature": 40, "split": 1}},
{"patternid": 634, "pattern": {"id": 0, "feature": 20, "split": 6}},
{"patternid": 246, "pattern": {"id": 0, "feature": 23, "split": 10}},
{"patternid": 542, "pattern": {"id": 0, "feature": 17, "split": 2}},
{"patternid": 493, "pattern": {"id": 0, "feature": 17, "split": 3}},
{"patternid": 341, "pattern": {"id": 0, "feature": 18, "split": 10}},
{"patternid": 579, "pattern": {"id": 0, "feature": 56, "split": 180}},
{"patternid": 47, "pattern": {"id": 0, "feature": 56, "split": 7}},
{"patternid": 43, "pattern": {"id": 0, "feature": 56, "split": 1710}},
{"patternid": 544, "pattern": {"id": 0, "feature": 56, "split": 311}},
{"patternid": 258, "pattern": {"id": 0, "feature": 56, "split": 290}},
{"patternid": 256, "pattern": {"id": 0, "feature": 56, "split": 43}},
{"patternid": 101, "pattern": {"id": 0, "feature": 25, "split": 1}},
{"patternid": 361, "pattern": {"id": 0, "feature": 15, "split": 0}},
{"patternid": 430, "pattern": {"id": 0, "feature": 40, "split": 1}},
{"patternid": 205, "pattern": {"id": 0, "feature": 17, "split": 0}},
{"patternid": 477, "pattern": {"id": 0, "feature": 56, "split": 97}},
{"patternid": 207, "pattern": {"id": 0, "feature": 56, "split": 80}},
{"patternid": 505, "pattern": {"id": 0, "feature": 54, "split": 15}},
{"patternid": 560, "pattern": {"id": 0, "feature": 35, "split": 0}},
{"patternid": 159, "pattern": {"id": 0, "feature": 56, "split": 99}},
{"patternid": 253, "pattern": {"id": 0, "feature": 13, "split": 2}},
{"patternid": 256, "pattern": {"id": 0, "feature": 56, "split": 43}},
{"patternid": 146, "pattern": {"id": 0, "feature": 44, "split": 4}},
{"patternid": 434, "pattern": {"id": 0, "feature": 52, "split": 2}},
{"patternid": 534, "pattern": {"id": 0, "feature": 24, "split": 5}},
{"patternid": 266, "pattern": {"id": 0, "feature": 31, "split": 0}},
{"patternid": 405, "pattern": {"id": 0, "feature": 56, "split": 386}},
{"patternid": 552, "pattern": {"id": 0, "feature": 4, "split": 4}},
{"patternid": 129, "pattern": {"id": 0, "feature": 56, "split": 248}},
{"patternid": 590, "pattern": {"id": 0, "feature": 16, "split": 0}},
{"patternid": 152, "pattern": {"id": 0, "feature": 17, "split": 1}},
{"patternid": 454, "pattern": {"id": 0, "feature": 56, "split": 129}},
{"patternid": 502, "pattern": {"id": 0, "feature": 21, "split": 9}},
{"patternid": 236, "pattern": {"id": 0, "feature": 55, "split": 88}},
{"patternid": 476, "pattern": {"id": 0, "feature": 55, "split": 34}},
{"patternid": 189, "pattern": {"id": 0, "feature": 6, "split": 4}},
{"patternid": 143, "pattern": {"id": 0, "feature": 21, "split": 3}},
{"patternid": 570, "pattern": {"id": 0, "feature": 56, "split": 77}},
{"patternid": 591, "pattern": {"id": 0, "feature": 56, "split": 36}},
{"patternid": 443, "pattern": {"id": 0, "feature": 56, "split": 1167}},
{"patternid": 94, "pattern": {"id": 0, "feature": 56, "split": 123}},
{"patternid": 596, "pattern": {"id": 0, "feature": 55, "split": 76}},
{"patternid": 361, "pattern": {"id": 0, "feature": 15, "split": 0}},
{"patternid": 452, "pattern": {"id": 0, "feature": 6, "split": 3}},
{"patternid": 426, "pattern": {"id": 0, "feature": 18, "split": 4}},
{"patternid": 200, "pattern": {"id": 0, "feature": 56, "split": 53}},
{"patternid": 46, "pattern": {"id": 0, "feature": 55, "split": 838}},
{"patternid": 154, "pattern": {"id": 0, "feature": 56, "split": 72}},
{"patternid": 627, "pattern": {"id": 0, "feature": 55, "split": 80}},
{"patternid": 263, "pattern": {"id": 0, "feature": 42, "split": 1}},
{"patternid": 224, "pattern": {"id": 0, "feature": 56, "split": 48}},
{"patternid": 297, "pattern": {"id": 0, "feature": 56, "split": 24}},
{"patternid": 56, "pattern": {"id": 0, "feature": 56, "split": 281}},
{"patternid": 154, "pattern": {"id": 0, "feature": 56, "split": 72}},
{"patternid": 8, "pattern": {"id": 0, "feature": 55, "split": 84}},
{"patternid": 344, "pattern": {"id": 0, "feature": 27, "split": 6}},
{"patternid": 315, "pattern": {"id": 0, "feature": 56, "split": 145}},
{"patternid": 356, "pattern": {"id": 0, "feature": 56, "split": 252}},
{"patternid": 379, "pattern": {"id": 0, "feature": 0, "split": 2}},
{"patternid": 558, "pattern": {"id": 0, "feature": 32, "split": 4}},
{"patternid": 180, "pattern": {"id": 0, "feature": 56, "split": 67}},
{"patternid": 611, "pattern": {"id": 0, "feature": 23, "split": 7}},
{"patternid": 344, "pattern": {"id": 0, "feature": 27, "split": 6}},
{"patternid": 145, "pattern": {"id": 0, "feature": 56, "split": 607}},
{"patternid": 450, "pattern": {"id": 0, "feature": 55, "split": 48}},
{"patternid": 86, "pattern": {"id": 0, "feature": 55, "split": 42}},
{"patternid": 125, "pattern": {"id": 0, "feature": 56, "split": 1524}},
{"patternid": 385, "pattern": {"id": 0, "feature": 55, "split": 175}},
{"patternid": 93, "pattern": {"id": 0, "feature": 55, "split": 60}},
{"patternid": 403, "pattern": {"id": 0, "feature": 56, "split": 139}},
{"patternid": 183, "pattern": {"id": 0, "feature": 5, "split": 3}},
{"patternid": 169, "pattern": {"id": 0, "feature": 56, "split": 629}},
{"patternid": 623, "pattern": {"id": 0, "feature": 18, "split": 13}},
{"patternid": 171, "pattern": {"id": 0, "feature": 56, "split": 202}},
{"patternid": 302, "pattern": {"id": 0, "feature": 56, "split": 51}},
{"patternid": 270, "pattern": {"id": 0, "feature": 54, "split": 11}},
{"patternid": 458, "pattern": {"id": 0, "feature": 56, "split": 214}},
{"patternid": 227, "pattern": {"id": 0, "feature": 56, "split": 66}},
{"patternid": 205, "pattern": {"id": 0, "feature": 17, "split": 0}},
{"patternid": 292, "pattern": {"id": 0, "feature": 20, "split": 4}},
{"patternid": 138, "pattern": {"id": 0, "feature": 56, "split": 95}},
{"patternid": 592, "pattern": {"id": 0, "feature": 46, "split": 1}},
{"patternid": 259, "pattern": {"id": 0, "feature": 56, "split": 61}},
{"patternid": 468, "pattern": {"id": 0, "feature": 55, "split": 16}},
{"patternid": 509, "pattern": {"id": 0, "feature": 13, "split": 1}},
{"patternid": 403, "pattern": {"id": 0, "feature": 56, "split": 139}},
{"patternid": 231, "pattern": {"id": 0, "feature": 9, "split": 0}},
{"patternid": 400, "pattern": {"id": 0, "feature": 55, "split": 67}},
{"patternid": 362, "pattern": {"id": 0, "feature": 55, "split": 36}},
{"patternid": 48, "pattern": {"id": 0, "feature": 56, "split": 10871}},
{"patternid": 17, "pattern": {"id": 0, "feature": 45, "split": 3}},
{"patternid": 54, "pattern": {"id": 0, "feature": 56, "split": 25}},
{"patternid": 427, "pattern": {"id": 0, "feature": 7, "split": 4}},
{"patternid": 354, "pattern": {"id": 0, "feature": 37, "split": 1}},
{"patternid": 469, "pattern": {"id": 0, "feature": 55, "split": 25}},
{"patternid": 450, "pattern": {"id": 0, "feature": 55, "split": 48}},
{"patternid": 302, "pattern": {"id": 0, "feature": 56, "split": 51}},
{"patternid": 583, "pattern": {"id": 0, "feature": 56, "split": 189}},
{"patternid": 133, "pattern": {"id": 0, "feature": 55, "split": 23}},
{"patternid": 500, "pattern": {"id": 0, "feature": 56, "split": 348}},
{"patternid": 201, "pattern": {"id": 0, "feature": 56, "split": 62}},
{"patternid": 111, "pattern": {"id": 0, "feature": 55, "split": 37}},
{"patternid": 166, "pattern": {"id": 0, "feature": 56, "split": 602}},
{"patternid": 472, "pattern": {"id": 0, "feature": 56, "split": 2065}},
{"patternid": 125, "pattern": {"id": 0, "feature": 56, "split": 1524}},
{"patternid": 383, "pattern": {"id": 0, "feature": 44, "split": 8}},
{"patternid": 560, "pattern": {"id": 0, "feature": 35, "split": 0}},
{"patternid": 454, "pattern": {"id": 0, "feature": 56, "split": 129}},
{"patternid": 352, "pattern": {"id": 0, "feature": 45, "split": 5}},
{"patternid": 102, "pattern": {"id": 0, "feature": 55, "split": 154}},
{"patternid": 7, "pattern": {"id": 0, "feature": 19, "split": 0}},
{"patternid": 227, "pattern": {"id": 0, "feature": 56, "split": 66}},
{"patternid": 311, "pattern": {"id": 0, "feature": 27, "split": 2}},
{"patternid": 401, "pattern": {"id": 0, "feature": 56, "split": 121}},
{"patternid": 368, "pattern": {"id": 0, "feature": 7, "split": 5}},
{"patternid": 355, "pattern": {"id": 0, "feature": 56, "split": 14}},
{"patternid": 241, "pattern": {"id": 0, "feature": 54, "split": 7}},
{"patternid": 576, "pattern": {"id": 0, "feature": 55, "split": 764}},
{"patternid": 290, "pattern": {"id": 0, "feature": 56, "split": 150}},
{"patternid": 646, "pattern": {"id": 0, "feature": 15, "split": 3}},
{"patternid": 636, "pattern": {"id": 0, "feature": 23, "split": 2}},
{"patternid": 362, "pattern": {"id": 0, "feature": 55, "split": 36}},
{"patternid": 431, "pattern": {"id": 0, "feature": 56, "split": 116}},
{"patternid": 478, "pattern": {"id": 0, "feature": 56, "split": 106}},
{"patternid": 136, "pattern": {"id": 0, "feature": 56, "split": 86}},
{"patternid": 601, "pattern": {"id": 0, "feature": 11, "split": 6}},
{"patternid": 386, "pattern": {"id": 0, "feature": 45, "split": 0}},
{"patternid": 527, "pattern": {"id": 0, "feature": 54, "split": 10}},
{"patternid": 617, "pattern": {"id": 0, "feature": 38, "split": 1}},
{"patternid": 240, "pattern": {"id": 0, "feature": 56, "split": 178}},
{"patternid": 358, "pattern": {"id": 0, "feature": 56, "split": 32}},
{"patternid": 519, "pattern": {"id": 0, "feature": 56, "split": 316}},
{"patternid": 339, "pattern": {"id": 0, "feature": 7, "split": 1}},
{"patternid": 413, "pattern": {"id": 0, "feature": 22, "split": 2}},
{"patternid": 34, "pattern": {"id": 0, "feature": 7, "split": 3}},
{"patternid": 440, "pattern": {"id": 0, "feature": 56, "split": 255}},
{"patternid": 392, "pattern": {"id": 0, "feature": 26, "split": 4}},
{"patternid": 381, "pattern": {"id": 0, "feature": 41, "split": 3}},
{"patternid": 115, "pattern": {"id": 0, "feature": 56, "split": 100}},
{"patternid": 111, "pattern": {"id": 0, "feature": 55, "split": 37}},
{"patternid": 460, "pattern": {"id": 0, "feature": 56, "split": 232}},
{"patternid": 327, "pattern": {"id": 0, "feature": 56, "split": 1}},
{"patternid": 581, "pattern": {"id": 0, "feature": 12, "split": 3}},
{"patternid": 297, "pattern": {"id": 0, "feature": 56, "split": 24}},
{"patternid": 508, "pattern": {"id": 0, "feature": 24, "split": 1}},
{"patternid": 463, "pattern": {"id": 0, "feature": 56, "split": 1562}},
{"patternid": 562, "pattern": {"id": 0, "feature": 56, "split": 459}},
{"patternid": 384, "pattern": {"id": 0, "feature": 56, "split": 647}},
{"patternid": 108, "pattern": {"id": 0, "feature": 55, "split": 19}},
{"patternid": 531, "pattern": {"id": 0, "feature": 32, "split": 0}},
{"patternid": 99, "pattern": {"id": 0, "feature": 41, "split": 0}},
{"patternid": 185, "pattern": {"id": 0, "feature": 56, "split": 85}},
{"patternid": 41, "pattern": {"id": 0, "feature": 0, "split": 0}},
{"patternid": 425, "pattern": {"id": 0, "feature": 56, "split": 525}},
{"patternid": 530, "pattern": {"id": 0, "feature": 43, "split": 0}},
{"patternid": 132, "pattern": {"id": 0, "feature": 55, "split": 14}},
{"patternid": 606, "pattern": {"id": 0, "feature": 20, "split": 2}},
{"patternid": 534, "pattern": {"id": 0, "feature": 24, "split": 5}},
{"patternid": 462, "pattern": {"id": 0, "feature": 22, "split": 1}},
{"patternid": 98, "pattern": {"id": 0, "feature": 52, "split": 0}},
{"patternid": 304, "pattern": {"id": 0, "feature": 26, "split": 10}},
{"patternid": 335, "pattern": {"id": 0, "feature": 56, "split": 275}},
{"patternid": 41, "pattern": {"id": 0, "feature": 0, "split": 0}},
{"patternid": 430, "pattern": {"id": 0, "feature": 40, "split": 1}},
{"patternid": 515, "pattern": {"id": 0, "feature": 56, "split": 69}},
{"patternid": 482, "pattern": {"id": 0, "feature": 55, "split": 119}},
{"patternid": 598, "pattern": {"id": 0, "feature": 8, "split": 1}},
{"patternid": 229, "pattern": {"id": 0, "feature": 17, "split": 4}},
{"patternid": 187, "pattern": {"id": 0, "feature": 48, "split": 1}},
{"patternid": 348, "pattern": {"id": 0, "feature": 30, "split": 2}},
{"patternid": 262, "pattern": {"id": 0, "feature": 55, "split": 74}},
{"patternid": 358, "pattern": {"id": 0, "feature": 56, "split": 32}},
{"patternid": 580, "pattern": {"id": 0, "feature": 54, "split": 9}},
{"patternid": 481, "pattern": {"id": 0, "feature": 56, "split": 115}},
{"patternid": 439, "pattern": {"id": 0, "feature": 3, "split": 2}},
{"patternid": 256, "pattern": {"id": 0, "feature": 56, "split": 43}},
{"patternid": 193, "pattern": {"id": 0, "feature": 54, "split": 17}},
{"patternid": 430, "pattern": {"id": 0, "feature": 40, "split": 1}},
{"patternid": 572, "pattern": {"id": 0, "feature": 56, "split": 324}},
{"patternid": 452, "pattern": {"id": 0, "feature": 6, "split": 3}},
{"patternid": 192, "pattern": {"id": 0, "feature": 54, "split": 8}},
{"patternid": 259, "pattern": {"id": 0, "feature": 56, "split": 61}},
{"patternid": 134, "pattern": {"id": 0, "feature": 56, "split": 504}},
{"patternid": 272, "pattern": {"id": 0, "feature": 4, "split": 1}},
{"patternid": 113, "pattern": {"id": 0, "feature": 56, "split": 91}},
{"patternid": 254, "pattern": {"id": 0, "feature": 56, "split": 34}},
{"patternid": 268, "pattern": {"id": 0, "feature": 56, "split": 173}},
{"patternid": 74, "pattern": {"id": 0, "feature": 56, "split": 631}},
{"patternid": 126, "pattern": {"id": 0, "feature": 2, "split": 3}},
{"patternid": 368, "pattern": {"id": 0, "feature": 7, "split": 5}},
{"patternid": 646, "pattern": {"id": 0, "feature": 15, "split": 3}},
{"patternid": 607, "pattern": {"id": 0, "feature": 54, "split": 4}},
{"patternid": 485, "pattern": {"id": 0, "feature": 51, "split": 5}},
{"patternid": 550, "pattern": {"id": 0, "feature": 56, "split": 176}},
{"patternid": 187, "pattern": {"id": 0, "feature": 48, "split": 1}},
{"patternid": 163, "pattern": {"id": 0, "feature": 6, "split": 0}},
{"patternid": 29, "pattern": {"id": 0, "feature": 55, "split": 43}},
{"patternid": 550, "pattern": {"id": 0, "feature": 56, "split": 176}},
{"patternid": 16, "pattern": {"id": 0, "feature": 56, "split": 3}},
{"patternid": 204, "pattern": {"id": 0, "feature": 56, "split": 71}},
{"patternid": 347, "pattern": {"id": 0, "feature": 56, "split": 140}},
{"patternid": 311, "pattern": {"id": 0, "feature": 27, "split": 2}},
{"patternid": 364, "pattern": {"id": 0, "feature": 49, "split": 2}},
{"patternid": 638, "pattern": {"id": 0, "feature": 56, "split": 1082}},
{"patternid": 204, "pattern": {"id": 0, "feature": 56, "split": 71}},
{"patternid": 67, "pattern": {"id": 0, "feature": 56, "split": 128}},
{"patternid": 128, "pattern": {"id": 0, "feature": 56, "split": 477}},
{"patternid": 37, "pattern": {"id": 0, "feature": 55, "split": 70}},
{"patternid": 155, "pattern": {"id": 0, "feature": 55, "split": 256}},
{"patternid": 421, "pattern": {"id": 0, "feature": 56, "split": 507}},
{"patternid": 469, "pattern": {"id": 0, "feature": 55, "split": 25}},
{"patternid": 306, "pattern": {"id": 0, "feature": 18, "split": 6}},
{"patternid": 441, "pattern": {"id": 0, "feature": 55, "split": 12}},
{"patternid": 636, "pattern": {"id": 0, "feature": 23, "split": 2}},
{"patternid": 463, "pattern": {"id": 0, "feature": 56, "split": 1562}},
{"patternid": 273, "pattern": {"id": 0, "feature": 56, "split": 429}},
{"patternid": 273, "pattern": {"id": 0, "feature": 56, "split": 429}},
{"patternid": 575, "pattern": {"id": 0, "feature": 55, "split": 90}},
{"patternid": 104, "pattern": {"id": 0, "feature": 56, "split": 6}},
{"patternid": 382, "pattern": {"id": 0, "feature": 56, "split": 391}},
{"patternid": 304, "pattern": {"id": 0, "feature": 26, "split": 10}},
{"patternid": 77, "pattern": {"id": 0, "feature": 22, "split": 0}},
{"patternid": 540, "pattern": {"id": 0, "feature": 56, "split": 64}},
{"patternid": 307, "pattern": {"id": 0, "feature": 7, "split": 6}},
{"patternid": 208, "pattern": {"id": 0, "feature": 56, "split": 318}},
{"patternid": 139, "pattern": {"id": 0, "feature": 55, "split": 41}},
{"patternid": 55, "pattern": {"id": 0, "feature": 55, "split": 29}},
{"patternid": 453, "pattern": {"id": 0, "feature": 21, "split": 1}},
{"patternid": 46, "pattern": {"id": 0, "feature": 55, "split": 838}},
{"patternid": 47, "pattern": {"id": 0, "feature": 56, "split": 7}},
{"patternid": 454, "pattern": {"id": 0, "feature": 56, "split": 129}},
{"patternid": 1, "pattern": {"id": 0, "feature": 55, "split": 66}},
{"patternid": 144, "pattern": {"id": 0, "feature": 21, "split": 12}},
{"patternid": 34, "pattern": {"id": 0, "feature": 7, "split": 3}},
{"patternid": 172, "pattern": {"id": 0, "feature": 51, "split": 7}},
{"patternid": 318, "pattern": {"id": 0, "feature": 56, "split": 163}},
{"patternid": 473, "pattern": {"id": 0, "feature": 9, "split": 4}},
{"patternid": 128, "pattern": {"id": 0, "feature": 56, "split": 477}},
{"patternid": 15, "pattern": {"id": 0, "feature": 4, "split": 2}},
{"patternid": 622, "pattern": {"id": 0, "feature": 56, "split": 296}},
{"patternid": 220, "pattern": {"id": 0, "feature": 56, "split": 201}},
{"patternid": 412, "pattern": {"id": 0, "feature": 56, "split": 4}},
{"patternid": 305, "pattern": {"id": 0, "feature": 15, "split": 10}},
{"patternid": 562, "pattern": {"id": 0, "feature": 56, "split": 459}},
{"patternid": 306, "pattern": {"id": 0, "feature": 18, "split": 6}},
{"patternid": 547, "pattern": {"id": 0, "feature": 6, "split": 1}},
{"patternid": 646, "pattern": {"id": 0, "feature": 15, "split": 3}},
{"patternid": 451, "pattern": {"id": 0, "feature": 56, "split": 111}},
{"patternid": 361, "pattern": {"id": 0, "feature": 15, "split": 0}},
{"patternid": 294, "pattern": {"id": 0, "feature": 23, "split": 0}},
{"patternid": 603, "pattern": {"id": 0, "feature": 55, "split": 103}},
{"patternid": 389, "pattern": {"id": 0, "feature": 45, "split": 9}},
{"patternid": 524, "pattern": {"id": 0, "feature": 21, "split": 4}},
{"patternid": 305, "pattern": {"id": 0, "feature": 15, "split": 10}},
{"patternid": 202, "pattern": {"id": 0, "feature": 55, "split": 8}},
{"patternid": 394, "pattern": {"id": 0, "feature": 15, "split": 4}},
{"patternid": 23, "pattern": {"id": 0, "feature": 56, "split": 39}},
{"patternid": 84, "pattern": {"id": 0, "feature": 55, "split": 33}},
{"patternid": 555, "pattern": {"id": 0, "feature": 51, "split": 8}},
{"patternid": 430, "pattern": {"id": 0, "feature": 40, "split": 1}},
{"patternid": 454, "pattern": {"id": 0, "feature": 56, "split": 129}},
{"patternid": 338, "pattern": {"id": 0, "feature": 18, "split": 1}},
{"patternid": 417, "pattern": {"id": 0, "feature": 55, "split": 17}},
{"patternid": 355, "pattern": {"id": 0, "feature": 56, "split": 14}},
{"patternid": 465, "pattern": {"id": 0, "feature": 56, "split": 250}},
{"patternid": 206, "pattern": {"id": 0, "feature": 28, "split": 0}},
{"patternid": 187, "pattern": {"id": 0, "feature": 48, "split": 1}},
{"patternid": 642, "pattern": {"id": 0, "feature": 1, "split": 1}},
{"patternid": 98, "pattern": {"id": 0, "feature": 52, "split": 0}},
{"patternid": 172, "pattern": {"id": 0, "feature": 51, "split": 7}},
{"patternid": 402, "pattern": {"id": 0, "feature": 56, "split": 130}},
{"patternid": 11, "pattern": {"id": 0, "feature": 11, "split": 5}},
{"patternid": 554, "pattern": {"id": 0, "feature": 56, "split": 441}},
{"patternid": 252, "pattern": {"id": 0, "feature": 24, "split": 2}},
{"patternid": 444, "pattern": {"id": 0, "feature": 55, "split": 30}},
{"patternid": 221, "pattern": {"id": 0, "feature": 51, "split": 6}},
{"patternid": 107, "pattern": {"id": 0, "feature": 55, "split": 10}},
{"patternid": 53, "pattern": {"id": 0, "feature": 3, "split": 10}},
{"patternid": 11, "pattern": {"id": 0, "feature": 11, "split": 5}},
{"patternid": 94, "pattern": {"id": 0, "feature": 56, "split": 123}},
{"patternid": 544, "pattern": {"id": 0, "feature": 56, "split": 311}},
{"patternid": 494, "pattern": {"id": 0, "feature": 5, "split": 1}},
{"patternid": 445, "pattern": {"id": 0, "feature": 56, "split": 511}},
{"patternid": 318, "pattern": {"id": 0, "feature": 56, "split": 163}},
{"patternid": 444, "pattern": {"id": 0, "feature": 55, "split": 30}},
{"patternid": 294, "pattern": {"id": 0, "feature": 23, "split": 0}},
{"patternid": 290, "pattern": {"id": 0, "feature": 56, "split": 150}},
{"patternid": 266, "pattern": {"id": 0, "feature": 31, "split": 0}},
{"patternid": 136, "pattern": {"id": 0, "feature": 56, "split": 86}},
{"patternid": 354, "pattern": {"id": 0, "feature": 37, "split": 1}},
{"patternid": 99, "pattern": {"id": 0, "feature": 41, "split": 0}},
{"patternid": 227, "pattern": {"id": 0, "feature": 56, "split": 66}},
{"patternid": 526, "pattern": {"id": 0, "feature": 20, "split": 8}},
{"patternid": 167, "pattern": {"id": 0, "feature": 54, "split": 13}},
{"patternid": 524, "pattern": {"id": 0, "feature": 21, "split": 4}},
{"patternid": 505, "pattern": {"id": 0, "feature": 54, "split": 15}},
{"patternid": 621, "pattern": {"id": 0, "feature": 56, "split": 58}},
{"patternid": 174, "pattern": {"id": 0, "feature": 56, "split": 211}},
{"patternid": 160, "pattern": {"id": 0, "feature": 56, "split": 108}},
{"patternid": 187, "pattern": {"id": 0, "feature": 48, "split": 1}},
{"patternid": 347, "pattern": {"id": 0, "feature": 56, "split": 140}},
{"patternid": 153, "pattern": {"id": 0, "feature": 28, "split": 1}},
{"patternid": 56, "pattern": {"id": 0, "feature": 56, "split": 281}},
{"patternid": 421, "pattern": {"id": 0, "feature": 56, "split": 507}},
{"patternid": 326, "pattern": {"id": 0, "feature": 34, "split": 1}},
{"patternid": 433, "pattern": {"id": 0, "feature": 41, "split": 2}},
{"patternid": 285, "pattern": {"id": 0, "feature": 56, "split": 65}},
{"patternid": 399, "pattern": {"id": 0, "feature": 56, "split": 112}},
{"patternid": 393, "pattern": {"id": 0, "feature": 55, "split": 40}},
{"patternid": 444, "pattern": {"id": 0, "feature": 55, "split": 30}},
{"patternid": 301, "pattern": {"id": 0, "feature": 15, "split": 1}},
{"patternid": 433, "pattern": {"id": 0, "feature": 41, "split": 2}},
{"patternid": 355, "pattern": {"id": 0, "feature": 56, "split": 14}}]
